airgram/__init__.py
airgram/ag.py
airgram-0.1.3.dist-info/DESCRIPTION.rst
airgram-0.1.3.dist-info/METADATA
airgram-0.1.3.dist-info/metadata.json
airgram-0.1.3.dist-info/RECORD
airgram-0.1.3.dist-info/top_level.txt
airgram-0.1.3.dist-info/WHEEL
