Metadata-Version: 2.0
Name: airgram
Version: 0.1.3
Summary: Wrapper for the airgram api
Home-page: https://github.com/the01/python-airgram
Author: d01
Author-email: jungflor@gmail.com
License: MIT License
Keywords: airgram
Platform: UNKNOWN
Classifier: Development Status :: 4 - Beta
Classifier: Intended Audience :: Developers
Classifier: License :: OSI Approved :: MIT License
Classifier: Natural Language :: English
Classifier: Programming Language :: Python :: 2
Classifier: Programming Language :: Python :: 2.7
Classifier: Programming Language :: Python :: 3
Classifier: Programming Language :: Python :: 3.3
Classifier: Programming Language :: Python :: 3.4
Requires-Dist: requests (>=2.7.0)
